[
    {
        "departamento": "Ahuachapán",
        "municipios": [
            {
                "nombre": "Ahuachapán Norte",
                "distritos": [
                    "Atiquizaya",
                    "El Refugio",
                    "San Lorenzo",
                    "Turín"
                ]
            },
            {
                "nombre": "Ahuachapán Centro",
                "distritos": [
                    "Ahuachapán",
                    "Apaneca",
                    "Concepción de Ataco",
                    "Tacuba"
                ]
            },
            {
                "nombre": "Ahuachapán Sur",
                "distritos": [
                    "Guaymango",
                    "Jujutla",
                    "San Francisco Menéndez",
                    "San Pedro Puxtla"
                ]
            }
        ]
    },
    {
        "departamento": "Cabañas",
        "municipios": [
            {
                "nombre": "Cabañas Este",
                "distritos": [
                    "Guacotecti",
                    "San Isidro",
                    "Victoria",
                    "Dolores",
                    "Sensuntepeque"
                ]
            },
            {
                "nombre": "Cabañas Oeste",
                "distritos": ["Cinquera", "Ilobasco", "Jutiapa", "Tejutepeque"]
            }
        ]
    },
    {
        "departamento": "Chalatenango",
        "municipios": [
            {
                "nombre": "Chalatenango Norte",
                "distritos": ["Citalá", "La Palma", "San Ignacio"]
            },
            {
                "nombre": "Chalatenango Centro",
                "distritos": [
                    "Agua Caliente",
                    "Dulce Nombre de María",
                    "El Paraíso",
                    "La Reina",
                    "Nueva Concepción",
                    "San Fernando",
                    "San Franscisco Morazán",
                    "San Rafael",
                    "Santa Rita",
                    "Tejutla"
                ]
            },
            {
                "nombre": "Chalatenango Sur",
                "distritos": [
                    "Arcatao",
                    "Azacualpa",
                    "Cancasque",
                    "Chalatenango",
                    "Comalapa",
                    "Concepción Quezaltepeque",
                    "El Carrizal",
                    "La Laguna",
                    "Las Vueltas",
                    "Las Flores",
                    "Nombre de Jesús",
                    "Nueva Trinidad",
                    "Ojos de Agua",
                    "Potonico",
                    "San Antonio de la Cruz",
                    "San Antonio Los Ranchos",
                    "San Francisco Lempa",
                    "San Isidro Labrador",
                    "San Luis del Carmen",
                    "San Miguel de Mercedes"
                ]
            }
        ]
    },
    {
        "departamento": "Cuscatlán",
        "municipios": [
            {
                "nombre": "Cuscatlán Norte",
                "distritos": [
                    "Suchitoto",
                    "San José Guayabal",
                    "Oratorio de Concepción",
                    "San Bartolomé Perulapía",
                    "San Pedro Perulapán"
                ]
            },
            {
                "nombre": "Cuscatlán Sur",
                "distritos": [
                    "Cojutepeque",
                    "Candelaria",
                    "El Carmen",
                    "El Rosario",
                    "Monte San Juan",
                    "San Cristóbal",
                    "San Rafael Cedros",
                    "San Ramón",
                    "Santa Cruz Analquito",
                    "Santa Cruz Michapa",
                    "Tenancingo"
                ]
            }
        ]
    },
    {
        "departamento": "La Libertad",
        "municipios": [
            {
                "nombre": "La Libertad Norte",
                "distritos": [
                    "Quezaltepeque",
                    "San Matías",
                    "San Pablo Tacachico"
                ]
            },
            {
                "nombre": "La Libertad Centro",
                "distritos": ["San Juan Opico", "Ciudad Arce"]
            },
            {
                "nombre": "La Libertad Oeste",
                "distritos": [
                    "Colón",
                    "Jayaque",
                    "Sacacoyo",
                    "Tepecoyo",
                    "Talnique"
                ]
            },
            {
                "nombre": "La Libertad Este",
                "distritos": [
                    "Antiguo Cuscatlán",
                    "Huizúcar",
                    "Nuevo Cuscatlán",
                    "San José Villanueva",
                    "Zaragoza"
                ]
            },
            {
                "nombre": "La Libertad Costa",
                "distritos": [
                    "Chiltiupán",
                    "Jicalapa",
                    "La Libertad",
                    "Tamanique",
                    "Teotepeque"
                ]
            },
            {
                "nombre": "La Libertad Sur",
                "distritos": ["Santa Tecla", "Comasagua"]
            }
        ]
    },
    {
        "departamento": "La Paz",
        "municipios": [
            {
                "nombre": "La Paz Oeste",
                "distritos": [
                    "Cuyultitán",
                    "Olocuilta",
                    "San Juan Talpa",
                    "San Luis Talpa",
                    "San Pedro Masahuat",
                    "Tapalhuaca",
                    "San Francisco Chinameca"
                ]
            },
            {
                "nombre": "La Paz Centro",
                "distritos": [
                    "El Rosario",
                    "Jerusalén",
                    "Mercedes La Ceiba",
                    "Paraíso de Osorio",
                    "San Antonio Masahuat",
                    "San Emigdio",
                    "San Juan Tepezontes",
                    "San Luis La Herradura",
                    "San Miguel Tepezontes",
                    "San Pedro Nonualco",
                    "Santa María Ostuma",
                    "Santiago Nonualco"
                ]
            },
            {
                "nombre": "La Paz Este",
                "distritos": [
                    "San Juan Nonualco",
                    "San Rafael Obrajuelo",
                    "Zacatecoluca"
                ]
            }
        ]
    },
    {
        "departamento": "La Unión",
        "municipios": [
            {
                "nombre": "La Unión Norte",
                "distritos": [
                    "Anamorós",
                    "Bolívar",
                    "Concepción de Oriente",
                    "El Sauce",
                    "Lislique",
                    "Nueva Esparta",
                    "Pasaquina",
                    "Polorós",
                    "San José",
                    "Santa Rosa de Lima"
                ]
            },
            {
                "nombre": "La Unión Sur",
                "distritos": [
                    "Conchagua",
                    "El Carmen",
                    "Intipucá",
                    "La Unión",
                    "Meanguera del Golfo",
                    "San Alejo",
                    "Yayantique",
                    "Yucuaiquín"
                ]
            }
        ]
    },
    {
        "departamento": "Morazán",
        "municipios": [
            {
                "nombre": "Morazán Norte",
                "distritos": [
                    "Arambala",
                    "Cacaopera",
                    "Corinto",
                    "El Rosario",
                    "Joateca",
                    "Jocoaitique",
                    "Meanguera",
                    "Perquín",
                    "San Fernando",
                    "San Isidro",
                    "Torola"
                ]
            },
            {
                "nombre": "Morazán Sur",
                "distritos": [
                    "Chilanga",
                    "Delicias de Concepción",
                    "El Divisadero",
                    "Gualococti",
                    "Guatajiagua",
                    "Jocoro",
                    "Lolotiquillo",
                    "Osicala",
                    "San Carlos",
                    "San Francisco Gotera",
                    "San Simón",
                    "Sensembra",
                    "Sociedad",
                    "Yamabal",
                    "Yoloaiquín"
                ]
            }
        ]
    },
    {
        "departamento": "San Miguel",
        "municipios": [
            {
                "nombre": "San Miguel Norte",
                "distritos": [
                    "Ciudad Barrios",
                    "Sesori",
                    "Nuevo Edén de San Juan",
                    "San Gerardo",
                    "San Luis de la Reina",
                    "Carolina",
                    "San Antonio",
                    "Chapeltique"
                ]
            },
            {
                "nombre": "San Miguel Centro",
                "distritos": [
                    "San Miguel",
                    "Comacarán",
                    "Uluazapa",
                    "Moncagua",
                    "Quelepa",
                    "Chirilagua"
                ]
            },
            {
                "nombre": "San Miguel Oeste",
                "distritos": [
                    "Chinameca",
                    "El Tránsito",
                    "Lolotique",
                    "Nueva Guadalupe",
                    "San Jorge",
                    "San Rafael Oriente"
                ]
            }
        ]
    },
    {
        "departamento": "San Salvador",
        "municipios": [
            {
                "nombre": "San Salvador Norte",
                "distritos": ["Aguilares", "El Paisnal", "Guazapa"]
            },
            {
                "nombre": "San Salvador Oeste",
                "distritos": ["Apopa", "Nejapa"]
            },
            {
                "nombre": "San Salvador Este",
                "distritos": [
                    "Ilopango",
                    "San Martín",
                    "Soyapango",
                    "Tonacatepeque"
                ]
            },
            {
                "nombre": "San Salvador Centro",
                "distritos": [
                    "Ayutuxtepeque",
                    "Mejicanos",
                    "Cuscatancingo",
                    "Ciudad Delgado",
                    "San Salvador"
                ]
            },
            {
                "nombre": "San Salvador Sur",
                "distritos": [
                    "San Marcos",
                    "Santo Tomás",
                    "Santiago Texacuangos",
                    "Panchimalco",
                    "Rosario de Mora"
                ]
            }
        ]
    },
    {
        "departamento": "San Vicente",
        "municipios": [
            {
                "nombre": "San Vicente Norte",
                "distritos": [
                    "Apastepeque",
                    "Santa Clara",
                    "San Ildefonso",
                    "San Esteban Catarina",
                    "San Sebastián",
                    "San Lorenzo",
                    "Santo Domingo"
                ]
            },
            {
                "nombre": "San Vicente Sur",
                "distritos": [
                    "San Vicente",
                    "Guadalupe",
                    "San Cayetano Istepeque",
                    "Tecoluca",
                    "Tepetitán",
                    "Verapaz"
                ]
            }
        ]
    },
    {
        "departamento": "Santa Ana",
        "municipios": [
            {
                "nombre": "Santa Ana Norte",
                "distritos": [
                    "Masahuat",
                    "Metapán",
                    "Santa Rosa Guachipilín",
                    "Texistepeque"
                ]
            },
            {
                "nombre": "Santa Ana Centro",
                "distritos": ["Santa Ana"]
            },
            {
                "nombre": "Santa Ana Este",
                "distritos": ["Coatepeque", "El Congo"]
            },
            {
                "nombre": "Santa Ana Oeste",
                "distritos": [
                    "Candelaria de la Frontera",
                    "Chalchuapa",
                    "El Porvenir",
                    "San Antonio Pajonal",
                    "San Sebastián Salitrillo",
                    "Santiago de la Frontera"
                ]
            }
        ]
    },
    {
        "departamento": "Sonsonate",
        "municipios": [
            {
                "nombre": "Sonsonate Norte",
                "distritos": [
                    "Juayúa",
                    "Nahuizalco",
                    "Salcoatitán",
                    "Santa Catarina Masahuat"
                ]
            },
            {
                "nombre": "Sonsonate Centro",
                "distritos": [
                    "Sonsonate",
                    "Sonzacate",
                    "Nahulingo",
                    "San Antonio del Monte",
                    "Santo Domingo de Guzmán"
                ]
            },
            {
                "nombre": "Sonsonate Este",
                "distritos": [
                    "Armenia",
                    "Caluco",
                    "Cuisnahuat",
                    "Izalco",
                    "San Julián",
                    "Santa Isabel Ishuatán"
                ]
            },
            {
                "nombre": "Sonsonate Oeste",
                "distritos": ["Acajutla"]
            }
        ]
    },
    {
        "departamento": "Usulután",
        "municipios": [
            {
                "nombre": "Usulután Norte",
                "distritos": [
                    "Alegría",
                    "Berlín",
                    "El Triunfo",
                    "Estanzuelas",
                    "Jucuapa",
                    "Mercedes Umaña",
                    "Nueva Granada",
                    "San Buenaventura",
                    "Santiago de María"
                ]
            },
            {
                "nombre": "Usulután Este",
                "distritos": [
                    "California",
                    "Concepción Batres",
                    "Ereguayquín",
                    "Jucuarán",
                    "Ozatlán",
                    "Santa Elena",
                    "San Dionisio",
                    "Santa María",
                    "Tecapán",
                    "Usulután"
                ]
            },
            {
                "nombre": "Usulután Oeste",
                "distritos": [
                    "Jiquilisco",
                    "Puerto El Triunfo",
                    "San Agustín",
                    "San Francisco Javier"
                ]
            }
        ]
    }
]
